{"name":"Verificar el ingreso correcto al sitio Éxito y elegir los productos de compra","id":"verificar-el-ingreso-correcto-al-sitio-éxito-y-elegir-los-productos-de-compra;verificar-el-ingreso-correcto-al-sitio-éxito-y-elegir-los-productos-de-compra","testSteps":[{"number":1,"description":"Dado que jhon ingreso a la pagina web del Éxito","duration":7577,"startTime":"2023-01-14T23:00:18.920-05:00[America/Bogota]","screenshots":[{"screenshot":"06c873844d4b2ad6e505c20bd16dfda5b3f55de39abd44583ceff07c256961fa.png"}],"result":"SUCCESS","precondition":false,"children":[{"number":2,"description":"jhon opens the Page exito","duration":6644,"startTime":"2023-01-14T23:00:19.342-05:00[America/Bogota]","screenshots":[{"screenshot":"11819669434ca5b89ef911b1df1ae99112fc6e3f1d89d9df833602fa0d47fd20.png"}],"result":"SUCCESS","precondition":false}]},{"number":3,"description":"Cuando elija una categoría y subcategoría","duration":3603,"startTime":"2023-01-14T23:00:26.498-05:00[America/Bogota]","screenshots":[{"screenshot":"2e3e1c370628ad01cacb35068340995fee2871df54019da458cb572b38af86f1.png"}],"result":"SUCCESS","precondition":false,"children":[{"number":4,"description":"jhon clicks on Menu principal","duration":672,"startTime":"2023-01-14T23:00:26.526-05:00[America/Bogota]","screenshots":[{"screenshot":"c73e9988b7f877242556e2432f88417962bcd567768182ffa47529c3f97a1b9d.png"}],"result":"SUCCESS","precondition":false},{"number":5,"description":"jhon clicks on CATEGORIA","duration":444,"startTime":"2023-01-14T23:00:27.201-05:00[America/Bogota]","screenshots":[{"screenshot":"de2d24b5c36f558f7cc75684dfb6b80629758ed8670110d915d9f364ca81f965.png"}],"result":"SUCCESS","precondition":false},{"number":6,"description":"jhon clicks on CATEGORIA_VIDEOJUEGOS","duration":939,"startTime":"2023-01-14T23:00:27.647-05:00[America/Bogota]","screenshots":[{"screenshot":"2a16def45352bc192c37414793ad2fb5eae4a34cb5eec6016c5f8dd197eacdb8.png"}],"result":"SUCCESS","precondition":false}]},{"number":7,"description":"Y Seleccione #5 productos aleatoreamente","duration":14413,"startTime":"2023-01-14T23:00:30.102-05:00[America/Bogota]","screenshots":[{"screenshot":"b2b86301b79456983c991ffd719c07555cbdef2d492006316edef0b27a52d9e5.png"}],"result":"SUCCESS","precondition":false,"children":[{"number":8,"description":"jhon clicks on Boton Agregar 10","duration":1375,"startTime":"2023-01-14T23:00:37.184-05:00[America/Bogota]","screenshots":[{"screenshot":"cdae86de1511be7951ae1390b4320594831c16ffc1edcc1421a184ca1ec81e2e.png"}],"result":"SUCCESS","precondition":false},{"number":9,"description":"jhon clicks on Boton Agregar 12","duration":1906,"startTime":"2023-01-14T23:00:38.562-05:00[America/Bogota]","screenshots":[{"screenshot":"7451211275c5e41d0e36a4ebe8e8020acc91590eb0e92a9adcc7c15b37264276.png"}],"result":"SUCCESS","precondition":false},{"number":10,"description":"jhon clicks on Boton Agregar 16","duration":1208,"startTime":"2023-01-14T23:00:40.472-05:00[America/Bogota]","screenshots":[{"screenshot":"72c4a8f4f31c5dc9835a74bf8bdff580aadc33f5f65a167d03bb73ac6c89e31f.png"}],"result":"SUCCESS","precondition":false},{"number":11,"description":"jhon clicks on Boton Agregar 17","duration":1305,"startTime":"2023-01-14T23:00:41.683-05:00[America/Bogota]","screenshots":[{"screenshot":"6d662da324f10e85b7c53e6c990dfaa15a248c04bd67fcc1242e5b8199483825.png"}],"result":"SUCCESS","precondition":false},{"number":12,"description":"jhon clicks on Boton Agregar 18","duration":1157,"startTime":"2023-01-14T23:00:42.992-05:00[America/Bogota]","screenshots":[{"screenshot":"bf79520d4accd279d0dfaa52512a5036823d2ec391c2c7907c10f4808261a6d5.png"}],"result":"SUCCESS","precondition":false}]},{"number":13,"description":"Y cada unos de los productos tenga cantidades aleatoreas entre 1-10","duration":5976,"startTime":"2023-01-14T23:00:44.517-05:00[America/Bogota]","screenshots":[{"screenshot":"4c82047dd95523d72203a63a301e63cbe4df044136061474fc947b487a1ccabf.png"}],"result":"SUCCESS","precondition":false,"children":[{"number":14,"description":"jhon clicks on icono del carrito","duration":4705,"startTime":"2023-01-14T23:00:45.570-05:00[America/Bogota]","screenshots":[{"screenshot":"4c82047dd95523d72203a63a301e63cbe4df044136061474fc947b487a1ccabf.png"}],"result":"SUCCESS","precondition":false}]},{"number":15,"description":"Entonces Se debe validar que el nombre de los productos agregados deberá ser igual que en el carrito","duration":210,"startTime":"2023-01-14T23:00:50.494-05:00[America/Bogota]","screenshots":[{"screenshot":"4c82047dd95523d72203a63a301e63cbe4df044136061474fc947b487a1ccabf.png"}],"result":"SUCCESS","precondition":false},{"number":16,"description":"Y El total de los precios de los productos agregados deberá ser igual que en el carrito","duration":206,"startTime":"2023-01-14T23:00:50.705-05:00[America/Bogota]","screenshots":[{"screenshot":"4c82047dd95523d72203a63a301e63cbe4df044136061474fc947b487a1ccabf.png"}],"result":"SUCCESS","precondition":false},{"number":17,"description":"Y Las cantidades de los productos agregados deberá ser igual que en el carrito","duration":195,"startTime":"2023-01-14T23:00:50.911-05:00[America/Bogota]","screenshots":[{"screenshot":"4c82047dd95523d72203a63a301e63cbe4df044136061474fc947b487a1ccabf.png"}],"result":"SUCCESS","precondition":false},{"number":18,"description":"Y El número de productos agregados debe ser igual que en el carrito","duration":185,"startTime":"2023-01-14T23:00:51.106-05:00[America/Bogota]","screenshots":[{"screenshot":"4c82047dd95523d72203a63a301e63cbe4df044136061474fc947b487a1ccabf.png"}],"result":"SUCCESS","precondition":false}],"userStory":{"id":"verificar-el-ingreso-correcto-al-sitio-éxito-y-elegir-los-productos-de-compra","storyName":"Verificar el ingreso correcto al sitio Éxito y elegir los productos de compra","path":"src/test/resources/features/prueba.feature","type":"feature"},"featureTag":{"name":"Features/Verificar el ingreso correcto al sitio Éxito y elegir los productos de compra","type":"feature"},"title":"Verificar el ingreso correcto al sitio Éxito y elegir los productos de compra","tags":[{"name":"","type":"CasoLogueo"},{"name":"Verificar el ingreso correcto al sitio éxito y elegir los productos de compra","type":"feature"},{"name":"HistoriaDeUsuario","type":"tag"}],"startTime":"2023-01-14T23:00:17.018-05:00[America/Bogota]","duration":34871,"projectKey":"","sessionId":"802977606065c6cf767c65fcddbbe7dc","driver":"chrome:jhon","manual":false,"testSource":"Cucumber","result":"SUCCESS"}